{"author_id":"1393777636103573505","conversation_id":"1423091213125750787","created_at":"2021-08-06T02:39:18.000Z","id":"1423473727833051137","in_reply_to_user_id":"1566580880","like_count":0,"quote_count":0,"reply_count":0,"retweet_count":0,"text":"@AluraOnline @pedromarins obrigada, pessoal ♥️"}
{"author_id":"2480541033","conversation_id":"1423459470810783745","created_at":"2021-08-06T01:42:39.000Z","id":"1423459470810783745","like_count":0,"quote_count":0,"reply_count":0,"retweet_count":0,"text":"So minha @AluraOnline tá diferente ou de mais alguém tá assim?\n\nCatReview! https://t.co/lnfAAQ24ug"}
{"author_id":"946646749761982465","conversation_id":"1423439266055692292","created_at":"2021-08-06T00:22:21.000Z","id":"1423439266055692292","like_count":0,"quote_count":0,"reply_count":0,"retweet_count":0,"text":"Boa noite só pra quem ganhou acesso a @AluraOnline da empresa❤️ https://t.co/ifSt4GKeL9"}
